perscache/__init__.py
perscache/_logger.py
perscache/cache.py
perscache/compatibility.py
perscache/serializers.py
perscache/storage.py
perscache-0.7.1.dist-info/AUTHORS
perscache-0.7.1.dist-info/LICENSE
perscache-0.7.1.dist-info/METADATA
perscache-0.7.1.dist-info/WHEEL
perscache-0.7.1.dist-info/pbr.json
perscache-0.7.1.dist-info/top_level.txt
perscache-0.7.1.dist-info/RECORD
