Metadata-Version: 2.2
Name: perscache
Version: 0.7.1
Summary: An easy to use decorator for persistent memoization: like `functools.lrucache`, but results can be saved in any format to any storage.
Home-page: https://github.com/leshchenko1979/perscache
Author: leshchenko1979
Author-email: leshchenko1979@gmail.com
License: MIT License
Classifier: Development Status :: 4 - Beta
Classifier: Intended Audience :: Developers
Classifier: License :: OSI Approved :: Apache Software License
Classifier: Natural Language :: English
Classifier: Operating System :: OS Independent
Classifier: Programming Language :: Python
Classifier: Programming Language :: Python :: 3.8
Classifier: Programming Language :: Python :: 3.9
Classifier: Programming Language :: Python :: 3.10
Classifier: Programming Language :: Python :: 3.11
Classifier: Programming Language :: Python :: 3.12
Classifier: Programming Language :: Python :: 3.13
Classifier: Programming Language :: Python :: Implementation :: CPython
Classifier: Topic :: Software Development
Requires-Python: >=3.6
License-File: LICENSE
License-File: AUTHORS
Requires-Dist: beartype>=0.10.0
Requires-Dist: cloudpickle
Requires-Dist: icontract
Dynamic: author
Dynamic: author-email
Dynamic: classifier
Dynamic: description
Dynamic: home-page
Dynamic: license
Dynamic: requires-dist
Dynamic: requires-python
Dynamic: summary
